IAMActionHunter/IAMActionHunter.py
IAMActionHunter/__init__.py
IAMActionHunter/configs/__init.py__
IAMActionHunter/configs/all.py
IAMActionHunter/lib/__init__.py
IAMActionHunter/lib/create_csv.py
IAMActionHunter/lib/data_collection.py
IAMActionHunter/lib/statement_parser.py
IAMActionHunter/lib/text_formatter.py
iamactionhunter-1.0.5.dist-info/entry_points.txt
iamactionhunter-1.0.5.dist-info/LICENSE
iamactionhunter-1.0.5.dist-info/WHEEL
iamactionhunter-1.0.5.dist-info/METADATA
iamactionhunter-1.0.5.dist-info/RECORD
