Metadata-Version: 2.1
Name: iamactionhunter
Version: 1.0.5
Summary: A query tool for AWS IAM policy statements.
Author: Dave Yesland with Rhino Security Labs
Requires-Python: >=3.9,<4.0
Classifier: Programming Language :: Python :: 3
Classifier: Programming Language :: Python :: 3.9
Classifier: Programming Language :: Python :: 3.10
Requires-Dist: boto3 (>=1.26.87,<2.0.0)
Requires-Dist: colorama (>=0.4.6,<0.5.0)
Requires-Dist: pandas (>=2.0.0,<3.0.0)
Requires-Dist: policyuniverse (>=1.5.0.20220613,<2.0.0.0)
